MO4D4PY/__init__.py
MO4D4PY/api.py
MO4D4PY/exceptions.py
MO4D4PY-0.0.1.dist-info/METADATA
MO4D4PY-0.0.1.dist-info/WHEEL
MO4D4PY-0.0.1.dist-info/top_level.txt
MO4D4PY-0.0.1.dist-info/RECORD
