Metadata-Version: 2.1
Name: MO4D4PY
Version: 0.0.1
Summary: Paquete para simplificar el uso de la API de MO4D en Python
Home-page: https://github.com/xxxxxx
Author: Nacho Alvarez
Author-email: joseignacio.alvarez@eviden.com
License: MIT
Keywords: python,EVIDEN,MO4D4PY
Classifier: Development Status :: 2 - Pre-Alpha
Classifier: Intended Audience :: Education
Classifier: Programming Language :: Python :: 2
Classifier: Programming Language :: Python :: 3
Classifier: Operating System :: MacOS :: MacOS X
Classifier: Operating System :: Microsoft :: Windows
Requires-Dist: requests
